watcmd/__init__.py
watcmd-0.2.0.dist-info/METADATA
watcmd-0.2.0.dist-info/WHEEL
watcmd-0.2.0.dist-info/entry_points.txt
watcmd-0.2.0.dist-info/licenses/LICENSE.txt
watcmd-0.2.0.dist-info/RECORD
