Metadata-Version: 2.4
Name: watcmd
Version: 0.2.0
Summary: A CLI tool to get UNIX commands from text explanations using AI
Project-URL: Github, https://github.com/alramalho/watcmd
Author-email: Alex Ramalho <alexandre.ramalho.1998@gmail.com>
License-File: LICENSE.txt
Classifier: License :: OSI Approved :: MIT License
Classifier: Operating System :: OS Independent
Classifier: Programming Language :: Python :: 3
Requires-Python: >=3.7
Requires-Dist: openai
